sauerkrautlm_colpali/__init__.py
sauerkrautlm_colpali/collators/__init__.py
sauerkrautlm_colpali/collators/visual_retriever_collator.py
sauerkrautlm_colpali/compression/__init__.py
sauerkrautlm_colpali/compression/token_pooling/__init__.py
sauerkrautlm_colpali/compression/token_pooling/base_token_pooling.py
sauerkrautlm_colpali/compression/token_pooling/hierarchical_token_pooling.py
sauerkrautlm_colpali/compression/token_pooling/lambda_token_pooling.py
sauerkrautlm_colpali/data/__init__.py
sauerkrautlm_colpali/data/dataset.py
sauerkrautlm_colpali/data/sampler.py
sauerkrautlm_colpali/interpretability/__init__.py
sauerkrautlm_colpali/interpretability/similarity_map_utils.py
sauerkrautlm_colpali/interpretability/similarity_maps.py
sauerkrautlm_colpali/loss/__init__.py
sauerkrautlm_colpali/loss/bi_encoder_losses.py
sauerkrautlm_colpali/loss/late_interaction_losses.py
sauerkrautlm_colpali/models/__init__.py
sauerkrautlm_colpali/models/lfm2/__init__.py
sauerkrautlm_colpali/models/lfm2/collfm2/__init__.py
sauerkrautlm_colpali/models/lfm2/collfm2/modeling_collfm2.py
sauerkrautlm_colpali/models/lfm2/collfm2/processing_collfm2.py
sauerkrautlm_colpali/models/ministral3/__init__.py
sauerkrautlm_colpali/models/ministral3/colministral3/__init__.py
sauerkrautlm_colpali/models/ministral3/colministral3/modeling_colministral3.py
sauerkrautlm_colpali/models/ministral3/colministral3/processing_colministral3.py
sauerkrautlm_colpali/models/qwen2_5/__init__.py
sauerkrautlm_colpali/models/qwen2_5/biqwen2_5/__init__.py
sauerkrautlm_colpali/models/qwen2_5/biqwen2_5/modeling_biqwen2_5.py
sauerkrautlm_colpali/models/qwen2_5/biqwen2_5/processing_biqwen2_5.py
sauerkrautlm_colpali/models/qwen2_5/colqwen2_5/__init__.py
sauerkrautlm_colpali/models/qwen2_5/colqwen2_5/modeling_colqwen2_5.py
sauerkrautlm_colpali/models/qwen2_5/colqwen2_5/processing_colqwen2_5.py
sauerkrautlm_colpali/models/qwen3/__init__.py
sauerkrautlm_colpali/models/qwen3/colqwen3/__init__.py
sauerkrautlm_colpali-0.1.0.dist-info/METADATA
sauerkrautlm_colpali-0.1.0.dist-info/WHEEL
sauerkrautlm_colpali-0.1.0.dist-info/licenses/LICENSE
sauerkrautlm_colpali-0.1.0.dist-info/RECORD
